synapse_token_authenticator/__init__.py
synapse_token_authenticator/claims_validator.py
synapse_token_authenticator/config.py
synapse_token_authenticator/token_authenticator.py
synapse_token_authenticator/utils.py
synapse_token_authenticator-0.12.0.dist-info/METADATA
synapse_token_authenticator-0.12.0.dist-info/WHEEL
synapse_token_authenticator-0.12.0.dist-info/licenses/LICENSE
synapse_token_authenticator-0.12.0.dist-info/RECORD
