Metadata-Version: 2.4
Name: synapse-token-authenticator
Version: 0.12.0
Summary: Synapse authentication module which allows for authenticating and registering using JWTs
Project-URL: Documentation, https://github.com/famedly/synapse-token-authenticator
Project-URL: Issues, https://github.com/famedly/synapse-token-authenticator/issues
Project-URL: Source, https://github.com/famedly/synapse-token-authenticator
Author-email: Sorunome <mail@sorunome.de>, Amanda Graven <amanda@graven.dev>, Jan Christian Grünhage <jan.christian@gruenhage.xyz>
License-Expression: AGPL-3.0-only
License-File: LICENSE
Classifier: Development Status :: 4 - Beta
Classifier: Programming Language :: Python
Classifier: Programming Language :: Python :: 3.9
Classifier: Programming Language :: Python :: 3.10
Classifier: Programming Language :: Python :: 3.11
Classifier: Programming Language :: Python :: Implementation :: CPython
Classifier: Programming Language :: Python :: Implementation :: PyPy
Requires-Python: >=3.11
Requires-Dist: jwcrypto
Requires-Dist: twisted
Requires-Dist: twisted==24.7.0
